Workbook

Sheet Matriz Ckeck LIst
C3: MATRIZ PARA COMPROBACIÓN REQUERIMIENTOS DE CALIDAD DE PROYECTO ACADEMICO
D5: SISTEMA: | E5: SISTEMA DE GESTION DE GIMNASIO (IRONCLAD BOX)
F6: Requerimientos Funcionales
B7: Nº | C7: CRITERIOS DE CALIDAD (Documento/Requerimientos) | E7: Status Nivel de Acuerdo | F7: CUC-ADM-01 Administrar la agenda de clases | I7: CUC-ADM-02 Gestionar Membresías y Pagos | K7: CUC-ADM-03 Gestionar Usuarios del Sistema | M7: CUC-ADM-04 Configurar Integraciones con Apps de Salud
B9: 1 | C9: Agreed | E9: OK | F9: 1. Videoconferencia de la entrevista 2. Minuta de la entrevista 3. Aceptación por videoconferencia | G9: OK | I9: 1. Videoconferencia de la entrevista 2. Minuta de la entrevista 3. Aceptación por videoconferencia | J9: OK | K9: 1. Videoconferencia de la entrevista 2. Minuta de la entrevista 3. Aceptación por videoconferencia | L9: OK | M9: 1. Videoconferencia de la entrevista 2. Minuta de la entrevista 3. Aceptación por videoconferencia
B10: 2 | C10: Ranked | E10: OK | F10: 1. En la descripción del caso de Uso se especifica la prioridad Alta | G10: OK | I10: 1. En la descripción del caso de Uso se especifica la prioridad Alta | J10: OK | K10: 1. En la descripción del caso de Uso se especifica la prioridad Media-Alta | L10: OK | M10: 1. El requisito está ponderado con una prioridad de nivel "Media".
B11: 3 | C11: Unambiguos | E11: OK | F11: 1. El flujo normal y alternativo están descritos sin ambigüedad: crear, editar, asignar entrenador, guardar. No hay términos confusos. | G11: OK | I11: 1. Redacción en lenguaje claro. 2. El tutor y el equipo interpretan de igual manera el caso de uso | J11: NOK | K11: 1.Inconsistencia de Alcance: El RF-ADM-03 de la ERS solo menciona gestionar "entrenadores y atletas" , mientras que el CUC-ADM-03 incluye también "administradores". Esto genera una contradicción grave sobre quién puede ser gestionado. | L11: OK | M11: 1. La descripción técnica de configurar credenciales API y definir datos a sincronizar permite una única interpretación para el equipo de desarrollo.
B12: 4 | C12: Valid and up-to date | E12: NOK | F12: 1. Corresponde a la versión actual del documento, refleja necesidades actuales del gimnasio y cambios que el cliente pide. | G12: NOK | I12: 1. Toda nueva información ha sido incorporada, se han incorporado los últimos cambios pedidos luego del feedback realizado por el cliente | J12: OK | K12: 1. Atiende la necesidad crítica de control de personal y seguridad del sistema mencionada en la problemática. | L12: OK | M12: 1. Incorpora información actual sobre las APIs de Google Fit, Apple y Samsung Health, incluyendo sus restricciones de estabilidad.
B13: 5 | C13: Correct | E13: OK | F13: 1. Coincide con los requisitos funcionales del módulo de administración. | G13: OK | I13: 1. Está alineado con los objetivos del sistema. 2. Refleja lo que realmente necesita el cliente. | J13: OK | K13: 1. Refleja la necesidad del cliente de centralizar la administración de cuentas de administradores, entrenadores y atletas. | L13: OK | M13: 1. Refleja la expectativa del cliente de automatizar la recolección de datos de salud de los atletas para mejorar el seguimiento.
B14: 6 | C14: Consistent | E14: OK | F14: 1. Documentación basada en modelos: Diagrama de Casos de Uso 2. Usa términos definidos previamente. | G14: OK | I14: 1. Documentación basada en modelos: Diagrama de Casos de Uso 2. Usa términos definidos previamente. | J14: NOK | K14: 1. Inconsistencia terminológica: La ERS usa "Altas/Bajas" y "CRUD". El caso de uso usa "Dar de baja" y "Desactivar". No hay un lenguaje unificado. | L14: OK | M14: 1. No presenta contradicciones con otros requisitos y utiliza la terminología estándar definida en el glosario del sistema.
B15: 7 | C15: Verifiable | E15: NOK | F15: 1. Requisito Medible 2. Falta Casos de Prueba | G15: NOK | I15: 1. Requisito Medible 2. Falta Casos de Prueba | J15: NOK | K15: 1. Requisito Medible. 2. Falta Casos de Prueba. | L15: NOK | M15: 1. Falta incluir los casos de prueba específicos que demuestren el cumplimiento del requisito con un esfuerzo razonable.
B16: 8 | C16: Realizable | E16: NOK | F16: 1. Funcionalidad contemplada en la estimación de costos. 2. No se ha desarrollado aún (fase de diseño de requerimientos). | G16: NOK | I16: 1. Funcionalidad contemplada en la estimación de costos. 2. No se ha desarrollado aún (fase de diseño de requerimientos). | J16: NOK | K16: 1. Funcionalidad contemplada en la estimación de costos. 2. No se ha desarrollado aún (fase de diseño de requerimientos). | L16: NOK | M16: 1. La funcionalidad aún no ha sido implementada/desarrollada en las condiciones actuales.
B17: 9 | C17: Traceable | E17: OK | F17: 1. Es claro el origen del requisito y sus relaciones con otros requisitos 2. Cuenta con un identificador único | G17: OK | I17: 1. Es claro el origen del requisito y sus relaciones con otros requisitos (matriz de trazabilidad cliente/casos de uso y casos de uso/casos de uso) 2. Cuenta con un identificador único | J17: OK | K17: 1. Cuenta con identificador único CUC-ADM-03. 2. El ID CUC-ADM-03 es rastreable al RF-ADM-03 de la SRS. | L17: OK | M17: 1. Tiene un origen claro vinculado al objetivo de seguimiento de atletas y posee el identificador único CUC-ADM-04.
B18: 10 | C18: Complete | E18: OK | F18: 1. Contiene toda la información necesaria (entradas, salidas, precondiciones, postcondiciones) para entender y diseñar la función. 2. Describe completamente la funcionalidad esperada. | G18: OK | I18: 1. Contiene toda la información necesaria (entradas, salidas, precondiciones, postcondiciones) para entender y diseñar la función. 2. Describe completamente la funcionalidad esperada. | J18: NOK | K18: 1. Falta flujo de búsqueda: No describe cómo el administrador localiza a un usuario específico en una lista potencialmente grande para editarlo o desactivarlo. | L18: OK | M18: 1. Trata todos los asuntos relevantes del requisito: entradas (credenciales), procesos (configuración) y salidas (sincronización activa).
B19: 11 | C19: Understandability | E19: OK | F19: 1. Se involucra al cliente 2. Existe glosario de términos | G19: OK | I19: 1. Se involucra al cliente 2. Existe glosario de términos | J19: OK | K19: 1. Se involucra al cliente 2. Existe glosario de términos | L19: OK | M19: 1. El flujo de pasos (del 1 al 6) es sencillo y fácil de entender para el equipo de desarrollo y el cliente.

Sheet MODELO LISTA DE COMPROBACION - 
B1: SISTEMA: | C1: Sistema De Gestión De Gimnasio (IronClad Box)
B2: FECHA: | C2: 46126
B3: AUTOR: | C3: Josue Solano
B4: REQUERIMIENTOS EVALUADOS : | C4: CUC-ADM-01 Administrar la agenda de clases
A6: CONTENIDO
A7: No. | B7: Pregunta | C7: SI | D7: NO
A8: 1 | B8: Todos los requerimientos relevantes se han documentado? | C8: X
A9: 2 | B9: Se han implementado las funciones requeridas? | C9: X
A10: 3 | B10: Existe algún mecanismo que permita seguir el impacto de dicho requerimiento a lo largo del resto de las actividades del ciclo productivo.? | D10: X
A11: 4 | B11: El origen de cada requerimento individual está claro ? | D11: X
A12: 5 | B12: Que tan facil es devolverse a los requerimientos? | C12: X
A13: 6 | B13: Los requerimientos reflejan las necesidades y deseos del cliente? | C13: X
A14: 7 | B14: No hay contradicciones entre los requerimientos? | C14: X
A15: 8 | B15: El requerimiento que se esta especificando contribuye a alcanzar un objetivo definido ? | C15: X
A16: 9 | B16: Existe un proceso acotado (en plazo y presupuesto) que permita determinar que el sistema construido satisface lo descrito en el propio requerimiento? | D16: X
A17: SUMATORIA: | C17: =COUNTA('MODELO LISTA DE COMPROBACION - '!$C$8:$C$16) -> 6 | D17: =COUNTA('MODELO LISTA DE COMPROBACION - '!$D$8:$D$16) -> 3
A18: PORCENTAJE : | C18: =C17/9 -> 0.66666667 | D18: =D17/9 -> 0.33333333
A20: DOCUMENTACIÓN
A21: No. | B21: Pregunta | C21: SI | D21: NO
A22: 1 | B22: Aplica un estandar para la documetación de requerimiento? | C22: X
A23: 2 | B23: Cumple con la estructura definida por el estandar? | C23: X
A24: 3 | B24: Utiliza un Glosario de términos normalizado? | D24: X
A25: 4 | B25: Los requerimientos Funcionales estan sujetos a una única interpretación? | C25: X
A26: 5 | B26: El modelo aplicado cumple con la sintaxis? | D26: X
A27: SUMATORIA: | C27: =COUNTA('MODELO LISTA DE COMPROBACION - '!$C$22:$C$26) -> 3 | D27: =COUNTA('MODELO LISTA DE COMPROBACION - '!$D$22:$D$26) -> 2
A28: PORCENTAJE : | C28: =C27/5 -> 0.6 | D28: =D27/5 -> 0.4
A30: NIVEL DE ACUERDO
A31: No. | B31: Pregunta | C31: SI | D31: NO
A32: 1 | B32: Todos los requerimientos han sido acordados con todos los interesados? | C32: X
A33: 2 | B33: Todos los requerimientos modificados han sido acordados por todos los implicados? | C33: X
A34: 3 | B34: Han sido resueltos todos los conflictos conocidos respectos de los requerimientos? | D34: X
A35: SUMATORIA: | C35: =COUNTA('MODELO LISTA DE COMPROBACION - '!$C$32:$C$34) -> 2 | D35: =COUNTA('MODELO LISTA DE COMPROBACION - '!$D$32:$D$34) -> 1
A36: PORCENTAJE : | C36: =C35/3 -> 0.66666667 | D36: =D35/3 -> 0.33333333
A40: RESUMEN
B41: CONTENIDO | C41: 67
B42: DOCUMENTACIÓN | C42: 60
B43: NIVEL DE ACUERDO | C43: 67

Sheet Hoja 2
B1: SISTEMA: | C1: Sistema De Gestión De Gimnasio (IronCladBox)
B2: FECHA: | C2: 46126
B3: AUTOR: | C3: Alexander Toapanta
B4: REQUERIMIENTOS EVALUADOS : | C4: CUC-ADM-02 Gestionar Membresías y Pagos
A6: CONTENIDO
A7: No. | B7: Pregunta | C7: SI | D7: NO
A8: 1 | B8: Todos los requerimientos relevantes se han documentado? | C8: X
A9: 2 | B9: Se han implementado las funciones requeridas? | D9: X
A10: 3 | B10: Existe algún mecanismo que permita seguir el impacto de dicho requerimiento a lo largo del resto de las actividades del ciclo productivo.? | C10: X
A11: 4 | B11: El origen de cada requerimento individual está claro ? | C11: X
A12: 5 | B12: Que tan facil es devolverse a los requerimientos? | C12: X
A13: 6 | B13: Los requerimientos reflejan las necesidades y deseos del cliente? | C13: X
A14: 7 | B14: No hay contradicciones entre los requerimientos? | D14: X
A15: 8 | B15: El requerimiento que se esta especificando contribuye a alcanzar un objetivo definido ? | C15: X
A16: 9 | B16: Existe un proceso acotado (en plazo y presupuesto) que permita determinar que el sistema construido satisface lo descrito en el propio requerimiento? | D16: X
A17: SUMATORIA: | C17: =COUNTA('Hoja 2'!$C$8:$C$16) -> 6 | D17: =COUNTA('Hoja 2'!$D$8:$D$16) -> 3
A18: PORCENTAJE : | C18: =C17/9 -> 0.66666667 | D18: =D17/9 -> 0.33333333
A20: DOCUMENTACIÓN
A21: No. | B21: Pregunta | C21: SI | D21: NO
A22: 1 | B22: Aplica un estandar para la documetación de requerimiento? | C22: X
A23: 2 | B23: Cumple con la estructura definida por el estandar? | D23: X
A24: 3 | B24: Utiliza un Glosario de términos normalizado? | C24: X
A25: 4 | B25: Los requerimientos Funcionales estan sujetos a una única interpretación? | D25: x
A26: 5 | B26: El modelo aplicado cumple con la sintaxis? | C26: X
A27: SUMATORIA: | C27: =COUNTA('Hoja 2'!$C$22:$C$26) -> 3 | D27: =COUNTA('Hoja 2'!$D$22:$D$26) -> 2
A28: PORCENTAJE : | C28: =C27/5 -> 0.6 | D28: =D27/5 -> 0.4
A30: NIVEL DE ACUERDO
A31: No. | B31: Pregunta | C31: SI | D31: NO
A32: 1 | B32: Todos los requerimientos han sido acordados con todos los interesados? | C32: X
A33: 2 | B33: Todos los requerimientos modificados han sido acordados por todos los implicados? | C33: X
A34: 3 | B34: Han sido resueltos todos los conflictos conocidos respectos de los requerimientos? | D34: X
A35: SUMATORIA: | C35: =COUNTA('Hoja 2'!$C$32:$C$34) -> 2 | D35: =COUNTA('Hoja 2'!$D$32:$D$34) -> 1
A36: PORCENTAJE : | C36: =C35/3 -> 0.66666667 | D36: =D35/3 -> 0.33333333
A40: RESUMEN
B41: CONTENIDO | C41: 67
B42: DOCUMENTACIÓN | C42: 60
B43: NIVEL DE ACUERDO | C43: 67

Sheet Hoja 3
B1: SISTEMA: | C1: Sistema De Gestión De Gimnasio (IronCladBox)
B2: FECHA: | C2: 46126
B3: AUTOR: | C3: Julio Blacio
B4: REQUERIMIENTOS EVALUADOS : | C4: CUC-ADM-03 Gestionar Usuarios del Sistema
A6: CONTENIDO
A7: No. | B7: Pregunta | C7: SI | D7: NO
A8: 1 | B8: Todos los requerimientos relevantes se han documentado? | C8: X
A9: 2 | B9: Se han implementado las funciones requeridas? | D9: X
A10: 3 | B10: Existe algún mecanismo que permita seguir el impacto de dicho requerimiento a lo largo del resto de las actividades del ciclo productivo.? | C10: X
A11: 4 | B11: El origen de cada requerimento individual está claro ? | C11: X
A12: 5 | B12: Que tan facil es devolverse a los requerimientos? | C12: X
A13: 6 | B13: Los requerimientos reflejan las necesidades y deseos del cliente? | C13: X
A14: 7 | B14: No hay contradicciones entre los requerimientos? | C14: X
A15: 8 | B15: El requerimiento que se esta especificando contribuye a alcanzar un objetivo definido ? | C15: X
A16: 9 | B16: Existe un proceso acotado (en plazo y presupuesto) que permita determinar que el sistema construido satisface lo descrito en el propio requerimiento? | D16: X
A17: SUMATORIA: | C17: =COUNTA('Hoja 3'!$C$8:$C$16) -> 7 | D17: =COUNTA('Hoja 3'!$D$8:$D$16) -> 2
A18: PORCENTAJE : | C18: =C17/9 -> 0.77777778 | D18: =D17/9 -> 0.22222222
A20: DOCUMENTACIÓN
A21: No. | B21: Pregunta | C21: SI | D21: NO
A22: 1 | B22: Aplica un estandar para la documetación de requerimiento? | C22: X
A23: 2 | B23: Cumple con la estructura definida por el estandar? | C23: X
A24: 3 | B24: Utiliza un Glosario de términos normalizado? | C24: X
A25: 4 | B25: Los requerimientos Funcionales estan sujetos a una única interpretación? | C25: X
A26: 5 | B26: El modelo aplicado cumple con la sintaxis? | C26: X
A27: SUMATORIA: | C27: =COUNTA('Hoja 3'!$C$22:$C$26) -> 5 | D27: =COUNTA('Hoja 3'!$D$22:$D$26) -> 0
A28: PORCENTAJE : | C28: =C27/5 -> 1 | D28: =D27/5 -> 0
A30: NIVEL DE ACUERDO
A31: No. | B31: Pregunta | C31: SI | D31: NO
A32: 1 | B32: Todos los requerimientos han sido acordados con todos los interesados? | C32: X
A33: 2 | B33: Todos los requerimientos modificados han sido acordados por todos los implicados? | C33: X
A34: 3 | B34: Han sido resueltos todos los conflictos conocidos respectos de los requerimientos? | C34: X
A35: SUMATORIA: | C35: =COUNTA('Hoja 3'!$C$32:$C$34) -> 3 | D35: =COUNTA('Hoja 3'!$D$32:$D$34) -> 0
A36: PORCENTAJE : | C36: =C35/3 -> 1 | D36: =D35/3 -> 0
A40: RESUMEN
B41: CONTENIDO | C41: 78
B42: DOCUMENTACIÓN | C42: 100
B43: NIVEL DE ACUERDO | C43: 100

Sheet Hoja 4
B1: SISTEMA: | C1: Sistema De Gestión De Gimnasio (IronCladBox)
B2: FECHA: | C2: 46126
B3: AUTOR: | C3: Kenned Sigcha
B4: REQUERIMIENTOS EVALUADOS : | C4: CUC-ADM-04 Gestionar Membresías y Pagos
A6: CONTENIDO
A7: No. | B7: Pregunta | C7: SI | D7: NO
A8: 1 | B8: Todos los requerimientos relevantes se han documentado? | C8: X
A9: 2 | B9: Se han implementado las funciones requeridas? | D9: X
A10: 3 | B10: Existe algún mecanismo que permita seguir el impacto de dicho requerimiento a lo largo del resto de las actividades del ciclo productivo.? | D10: X
A11: 4 | B11: El origen de cada requerimento individual está claro ? | C11: X
A12: 5 | B12: Que tan facil es devolverse a los requerimientos? | C12: X
A13: 6 | B13: Los requerimientos reflejan las necesidades y deseos del cliente? | C13: X
A14: 7 | B14: No hay contradicciones entre los requerimientos? | C14: X
A15: 8 | B15: El requerimiento que se esta especificando contribuye a alcanzar un objetivo definido ? | C15: X
A16: 9 | B16: Existe un proceso acotado (en plazo y presupuesto) que permita determinar que el sistema construido satisface lo descrito en el propio requerimiento? | D16: X
A17: SUMATORIA: | C17: =COUNTA('Hoja 4'!$C$8:$C$16) -> 6 | D17: =COUNTA('Hoja 4'!$D$8:$D$16) -> 3
A18: PORCENTAJE : | C18: =C17/9 -> 0.66666667 | D18: =D17/9 -> 0.33333333
A20: DOCUMENTACIÓN
A21: No. | B21: Pregunta | C21: SI | D21: NO
A22: 1 | B22: Aplica un estandar para la documetación de requerimiento? | C22: X
A23: 2 | B23: Cumple con la estructura definida por el estandar? | C23: X
A24: 3 | B24: Utiliza un Glosario de términos normalizado? | C24: X
A25: 4 | B25: Los requerimientos Funcionales estan sujetos a una única interpretación? | C25: X
A26: 5 | B26: El modelo aplicado cumple con la sintaxis? | D26: X
A27: SUMATORIA: | C27: =COUNTA('Hoja 4'!$C$22:$C$26) -> 4 | D27: =COUNTA('Hoja 4'!$D$22:$D$26) -> 1
A28: PORCENTAJE : | C28: =C27/5 -> 0.8 | D28: =D27/5 -> 0.2
A30: NIVEL DE ACUERDO
A31: No. | B31: Pregunta | C31: SI | D31: NO
A32: 1 | B32: Todos los requerimientos han sido acordados con todos los interesados? | C32: X
A33: 2 | B33: Todos los requerimientos modificados han sido acordados por todos los implicados? | C33: X
A34: 3 | B34: Han sido resueltos todos los conflictos conocidos respectos de los requerimientos? | C34: X
A35: SUMATORIA: | C35: =COUNTA('Hoja 4'!$C$32:$C$34) -> 3 | D35: =COUNTA('Hoja 4'!$D$32:$D$34) -> 0
A36: PORCENTAJE : | C36: =C35/3 -> 1 | D36: =D35/3 -> 0
A40: RESUMEN
B41: CONTENIDO | C41: 67
B42: DOCUMENTACIÓN | C42: 80
B43: NIVEL DE ACUERDO | C43: 100

Sheet RECOMENDACIONES 
A1: PREGUNTA | B1: RECOMENDACIÓN
A2: ¿Se ha generado una minuta oficial por cada videoconferencia de descubrimiento con tutor, cliente (dueño del gimnasio) y equipo? | B2: Crear una plantilla con: fecha, asistentes, temas tratados, acuerdos y pendientes (ej. DocuSign, Google Forms con acuse). | C2: CUC-ADM-01
A3: ¿Existe un procedimiento de objeción o cambio posterior a la firma? | B3: Adjuntar una tabla donde cada cambio solicitado quede documentado con fecha, responsable y aprobación.
A4: ¿Se ha definido el comportamiento del sistema cuando una membresía vence un fin de semana o feriado? | B4: Establecer regla de negocio explícita en la minuta: "Si el vencimiento cae en día no laborable, el sistema extenderá automáticamente el acceso hasta el siguiente día hábil a las 23:59 sin penalización. | C4: CUC-ADM-02
A5: ¿Se ha especificado un límite de tiempo para que el administrador pueda corregir un pago registrado por error? | B5: Agregar excepción: "Ventana de anulación de 5 minutos. Pasado ese tiempo, el pago erróneo deberá gestionarse como Nota de Crédito manual con justificación obligatoria y aprobación de segundo administrador.
A6: ¿Se ha contemplado un mecanismo de respaldo si el Sistema de Pagos (Secundary Actor) está fuera de línea? | B6: Incluir en Restricciones: "Modo Offline para registro de efectivo con sincronización diferida. Si la pasarela falla, el sistema notificará 'Pago Pendiente de Confirmación Bancaria' y no activará la membresía hasta verificación automática.
A7: ¿El Caso de Uso contempla funcionalidades de búsqueda y filtrado indispensables para el volumen de datos previsto? | B7: Incorporar un paso de búsqueda y filtrado en el flujo de edición de usuarios, dado que el sistema debe gestionar de manera eficiente a más de 200 atletas y el flujo actual solo menciona "seleccionar de la lista". | C7: CUC-ADM-03
A8: ¿Se han incluido los casos de prueba necesarios para validar las restricciones de seguridad mencionadas? | B8: Elaborar una sección de Casos de Prueba específicos que verifiquen las excepciones detalladas, como el "Intento de auto-eliminación" o el "Error al enviar email de activación".
A9: ¿Coincide el nivel de prioridad entre la matriz de requerimientos funcionales y el detalle individual del Caso de Uso? | B9: Sincronizar la prioridad del CUC-ADM-03 (registrada como "Media-Alta") para que sea "Alta", alineándose estrictamente con lo establecido para el requerimiento RF-ADM-03 en la tabla de la ERS.
A10: ¿Se han implementado las funciones requeridas? | B10: Establecer un cronograma de desarrollo para el módulo de integraciones (API) y realizar una prueba de concepto (PoC) inicial con Google Fit para asegurar la viabilidad técnica antes de la fase de construcción. | C10: CUC-ADM-04
A11: ¿Existe algún mecanismo que permita seguir el impacto del requerimiento? | B11: Crear una Matriz de Trazabilidad de Requisitos que vincule el CUC-ADM-04 con los casos de prueba y los componentes de código, permitiendo evaluar el impacto ante cambios en las APIs de terceros (Samsung, Apple, Google).
A12: ¿Existe un proceso acotado que permita determinar que el sistema satisface lo descrito? | B12: Diseñar e incluir en la documentación un Plan de Pruebas de Integración que detalle los criterios de aceptación (ej: sincronización exitosa de pasos y frecuencia cardíaca en menos de 5 segundos).
